opencv_stream/__init__.py
opencv_stream/fps_drawer.py
opencv_stream/fps_writer.py
opencv_stream/model_schema.py
opencv_stream/option.py
opencv_stream/utils.py
opencv_stream/video.py
opencv_stream-0.1.1.dist-info/LICENSE
opencv_stream-0.1.1.dist-info/METADATA
opencv_stream-0.1.1.dist-info/WHEEL
opencv_stream-0.1.1.dist-info/top_level.txt
opencv_stream-0.1.1.dist-info/RECORD
