Metadata-Version: 2.1
Name: opencv-stream
Version: 0.1.1
Summary: Wrapper over opencv for video processing and API development
Author: Olivier
Author-email: luowensheng2018@gmail.com
Keywords: python,video,stream,AI,API
Classifier: Development Status :: 1 - Planning
Classifier: Intended Audience :: Developers
Classifier: Programming Language :: Python :: 3
Classifier: Operating System :: Unix
Classifier: Operating System :: MacOS :: MacOS X
Classifier: Operating System :: Microsoft :: Windows
License-File: LICENSE
Requires-Dist: opencv-python
Requires-Dist: numpy
